README.txt
setup.py
bzconsole/__init__.py
bzconsole/api.py
bzconsole/command.py
bzconsole/main.py
bzconsole/utils.py
bzconsole.egg-info/PKG-INFO
bzconsole.egg-info/SOURCES.txt
bzconsole.egg-info/dependency_links.txt
bzconsole.egg-info/entry_points.txt
bzconsole.egg-info/not-zip-safe
bzconsole.egg-info/requires.txt
bzconsole.egg-info/top_level.txt