Metadata-Version: 1.0
Name: bzconsole
Version: 0.3.3
Summary: console API to bugzilla
Home-page: http://k0s.org/mozilla/hg/bzconsole
Author: Jeff Hammel
Author-email: jhammel@mozilla.com
License: MPL
Platform: UNKNOWN
